{
	"forge_marker": 1,
	"defaults": {
		"transform": "forge:default-block",
		"model": "minecraft:cube_all"
	},
	"variants": {
		"variant": {
			"off": {"textures":{"all":"correlated:blocks/dungeon/lithographene.off"}},
			"off_variant": {"textures":{"all":"correlated:blocks/dungeon/lithographene.off.variant"}},
			"on": {"textures":{"all":"correlated:blocks/dungeon/lithographene.on"}},
			"on_variant": {"textures":{"all":"correlated:blocks/dungeon/lithographene.on.variant"}}
		},
		"inventory": [{"textures":{"all":"correlated:blocks/dungeon/lithographene.off"}}],
		
		"inventory0": [{"textures":{"all":"correlated:blocks/dungeon/lithographene.off"}}],
		"inventory1": [{"textures":{"all":"correlated:blocks/dungeon/lithographene.off.variant"}}],
		"inventory2": [{"textures":{"all":"correlated:blocks/dungeon/lithographene.on"}}],
		"inventory3": [{"textures":{"all":"correlated:blocks/dungeon/lithographene.on.variant"}}]
	}
}