{
	"forge_marker": 1,
	"defaults": {
		"model": "minecraft:orientable",
		"textures": {
			"top": "correlatedpotentialistics:blocks/top",
			"side": "correlatedpotentialistics:blocks/side",
			"front": "correlatedpotentialistics:blocks/terminal"
		}
	},
	"variants": {
		"lit": {"true":{},"false":{}},
		"floppy": {"true":{},"false":{}},
		"facing": {
			"north": {},
			"east": {
				"y": 90
			},
			"south": {
				"y": 180
			},
			"west": {
				"y": 270
			}
		},
		"inventory": {
			"transform": "forge:default-block",
			"model": "correlatedpotentialistics:double_cube",
			"textures": {
				"north_base": "correlatedpotentialistics:blocks/terminal",
				"east_base": "correlatedpotentialistics:blocks/top",
				"south_base": "correlatedpotentialistics:blocks/top",
				"west_base": "correlatedpotentialistics:blocks/top",
				"up_base": "correlatedpotentialistics:blocks/top",
				"down_base": "correlatedpotentialistics:blocks/top",
				"north_overlay": "correlatedpotentialistics:blocks/terminal_glow",
				"east_overlay": "correlatedpotentialistics:blocks/top",
				"south_overlay": "correlatedpotentialistics:blocks/top",
				"west_overlay": "correlatedpotentialistics:blocks/top",
				"up_overlay": "correlatedpotentialistics:blocks/top",
				"down_overlay": "correlatedpotentialistics:blocks/top"
			}
		}
	}
}